docs/CONTRIBUTING.md
docs/examples/basic_usage.py
docs/examples/batch_crawling.py
docs/examples/custom_config.py
vnewsapi/__init__.py
vnewsapi/exceptions.py
vnewsapi/api/__init__.py
vnewsapi/api/enhanced.py
vnewsapi/config/__init__.py
vnewsapi/config/sites.py
vnewsapi/core/__init__.py
vnewsapi/core/base.py
vnewsapi/core/batch.py
vnewsapi/core/crawler.py
vnewsapi/core/rss.py
vnewsapi/core/sitemap.py
vnewsapi/utils/__init__.py
vnewsapi/utils/browser_profiles.py
vnewsapi/utils/cleaner.py
vnewsapi/utils/client.py
vnewsapi/utils/logger.py
vnewsapi/utils/parser.py
vnewsapi/utils/user_agent.py
vnewsapi-0.1.0.dist-info/licenses/LICENSE
vnewsapi-0.1.0.dist-info/METADATA
vnewsapi-0.1.0.dist-info/WHEEL
vnewsapi-0.1.0.dist-info/top_level.txt
vnewsapi-0.1.0.dist-info/RECORD
