Metadata-Version: 2.4
Name: vnewsapi
Version: 0.1.0
Summary: A Python library for crawling Vietnamese financial news from major news websites
Home-page: https://github.com/Hoanganhvu123/vnewsapi
Author: vnewsapi contributors
Author-email: vnewsapi contributors <support@vnewsapi.com>
License-Expression: MIT
Project-URL: Homepage, https://github.com/Hoanganhvu123/vnewsapi
Project-URL: Documentation, https://github.com/Hoanganhvu123/vnewsapi#readme
Project-URL: Repository, https://github.com/Hoanganhvu123/vnewsapi
Project-URL: Issues, https://github.com/Hoanganhvu123/vnewsapi/issues
Keywords: vietnam,news,crawler,finance,rss,sitemap,scraping
Classifier: Development Status :: 3 - Alpha
Classifier: Intended Audience :: Developers
Classifier: Intended Audience :: Financial and Insurance Industry
Classifier: Topic :: Software Development :: Libraries :: Python Modules
Classifier: Topic :: Internet :: WWW/HTTP :: Indexing/Search
Classifier: Topic :: Text Processing :: Markup :: HTML
Classifier: Programming Language :: Python :: 3
Classifier: Programming Language :: Python :: 3.10
Classifier: Programming Language :: Python :: 3.11
Classifier: Programming Language :: Python :: 3.12
Classifier: Operating System :: OS Independent
Classifier: Natural Language :: Vietnamese
Classifier: Natural Language :: English
Requires-Python: >=3.10
License-File: LICENSE
Requires-Dist: requests>=2.31.0
Requires-Dist: beautifulsoup4>=4.12.0
Requires-Dist: lxml>=4.9.0
Requires-Dist: feedparser>=6.0.0
Requires-Dist: html2text>=2020.1.16
Requires-Dist: pandas>=2.0.0
Requires-Dist: python-dateutil>=2.8.0
Provides-Extra: test
Requires-Dist: pytest>=7.0.0; extra == "test"
Requires-Dist: pytest-cov>=4.0.0; extra == "test"
Requires-Dist: pytest-asyncio>=0.21.0; extra == "test"
Requires-Dist: pytest-timeout>=2.1.0; extra == "test"
Provides-Extra: dev
Requires-Dist: black>=23.0.0; extra == "dev"
Requires-Dist: flake8>=6.0.0; extra == "dev"
Requires-Dist: mypy>=1.0.0; extra == "dev"
Requires-Dist: build>=0.10.0; extra == "dev"
Requires-Dist: twine>=4.0.0; extra == "dev"
Dynamic: author
Dynamic: home-page
Dynamic: license-file
Dynamic: requires-python
